<?xml version="1.0" encoding="UTF-8"?>
<sbml xmlns="http://www.sbml.org/sbml/level3/version1/core" level="3" version="1">
  <model id="goldbeter1" name="goldbeter1">
    <listOfCompartments>
      <compartment metaid="metaid_0" sboTerm="SBO:0000410" id="default_compartment" name="default_compartment" spatialDimensions="3" size="1" constant="true"/>
    </listOfCompartments>
    <listOfSpecies>
      <species metaid="metaid_1" id="alpha" name="alpha" compartment="default_compartment" initialConcentration="100" hasOnlySubstanceUnits="false" boundaryCondition="false" constant="false"/>
      <species metaid="metaid_2" id="gamma" name="gamma" compartment="default_compartment" initialConcentration="20" hasOnlySubstanceUnits="false" boundaryCondition="false" constant="false"/>
      <species metaid="metaid_3" id="p" name="p" compartment="default_compartment" initialConcentration="0" hasOnlySubstanceUnits="false" boundaryCondition="true" constant="false"/>
      <species metaid="metaid_4" id="s" name="s" compartment="default_compartment" initialConcentration="0" hasOnlySubstanceUnits="false" boundaryCondition="true" constant="false"/>
    </listOfSpecies>
    <listOfParameters>
      <parameter metaid="metaid_5" id="EXTERNAL" name="EXTERNAL" value="0" constant="false"/>
      <parameter metaid="metaid_6" id="c" name="c" value="1e-05" constant="false"/>
      <parameter metaid="metaid_7" id="el" name="el" value="1000000" constant="false"/>
      <parameter metaid="metaid_8" id="ep" name="ep" value="0.9090909" constant="false"/>
      <parameter metaid="metaid_9" id="es" name="es" value="0.9090909" constant="false"/>
      <parameter metaid="metaid_10" id="k1" name="k1" value="0.7" constant="false"/>
      <parameter metaid="metaid_11" id="k2" name="k2" value="3.98" constant="false"/>
      <parameter metaid="metaid_12" id="k3" name="k3" value="0.1" constant="false"/>
      <parameter metaid="metaid_13" id="ve" name="ve" value="1" constant="false"/>
    </listOfParameters>
    <listOfReactions>
      <reaction metaid="metaid_16" id="v1" name="v1" reversible="true" fast="false">
        <listOfReactants>
          <speciesReference metaid="metaid_14" species="s" stoichiometry="1" constant="true"/>
        </listOfReactants>
        <listOfProducts>
          <speciesReference metaid="metaid_15" species="alpha" stoichiometry="1" constant="true"/>
        </listOfProducts>
        <kineticLaw>
          <math xmlns="http://www.w3.org/1998/Math/MathML">
            <ci> k1 </ci>
          </math>
        </kineticLaw>
      </reaction>
      <reaction metaid="metaid_21" id="v2" name="v2" reversible="true" fast="false">
        <listOfReactants>
          <speciesReference metaid="metaid_17" species="alpha" stoichiometry="1" constant="true"/>
        </listOfReactants>
        <listOfProducts>
          <speciesReference metaid="metaid_18" species="gamma" stoichiometry="1" constant="true"/>
        </listOfProducts>
        <listOfModifiers>
          <modifierSpeciesReference metaid="metaid_19" sboTerm="SBO:0000011" species="gamma"/>
          <modifierSpeciesReference metaid="metaid_20" sboTerm="SBO:0000534" species="gamma"/>
        </listOfModifiers>
        <kineticLaw>
          <math xmlns="http://www.w3.org/1998/Math/MathML">
            <apply>
              <divide/>
              <apply>
                <times/>
                <ci> k2 </ci>
                <apply>
                  <plus/>
                  <apply>
                    <times/>
                    <ci> alpha </ci>
                    <ci> es </ci>
                    <apply>
                      <plus/>
                      <cn type="integer"> 1 </cn>
                      <apply>
                        <times/>
                        <ci> alpha </ci>
                        <ci> es </ci>
                      </apply>
                    </apply>
                    <apply>
                      <power/>
                      <apply>
                        <plus/>
                        <cn type="integer"> 1 </cn>
                        <ci> gamma </ci>
                      </apply>
                      <cn type="integer"> 2 </cn>
                    </apply>
                  </apply>
                  <apply>
                    <times/>
                    <ci> el </ci>
                    <ci> ve </ci>
                    <ci> alpha </ci>
                    <ci> c </ci>
                    <ci> ep </ci>
                    <apply>
                      <plus/>
                      <cn type="integer"> 1 </cn>
                      <apply>
                        <times/>
                        <ci> alpha </ci>
                        <ci> c </ci>
                        <ci> ep </ci>
                      </apply>
                    </apply>
                  </apply>
                </apply>
              </apply>
              <apply>
                <plus/>
                <apply>
                  <times/>
                  <ci> el </ci>
                  <apply>
                    <power/>
                    <apply>
                      <plus/>
                      <cn type="integer"> 1 </cn>
                      <apply>
                        <times/>
                        <ci> alpha </ci>
                        <ci> c </ci>
                        <ci> ep </ci>
                      </apply>
                    </apply>
                    <cn type="integer"> 2 </cn>
                  </apply>
                </apply>
                <apply>
                  <times/>
                  <apply>
                    <power/>
                    <apply>
                      <plus/>
                      <cn type="integer"> 1 </cn>
                      <ci> gamma </ci>
                    </apply>
                    <cn type="integer"> 2 </cn>
                  </apply>
                  <apply>
                    <power/>
                    <apply>
                      <plus/>
                      <cn type="integer"> 1 </cn>
                      <apply>
                        <times/>
                        <ci> alpha </ci>
                        <ci> es </ci>
                      </apply>
                    </apply>
                    <cn type="integer"> 2 </cn>
                  </apply>
                </apply>
              </apply>
            </apply>
          </math>
        </kineticLaw>
      </reaction>
      <reaction metaid="metaid_25" id="v3" name="v3" reversible="true" fast="false">
        <listOfReactants>
          <speciesReference metaid="metaid_22" species="gamma" stoichiometry="1" constant="true"/>
        </listOfReactants>
        <listOfProducts>
          <speciesReference metaid="metaid_23" species="p" stoichiometry="1" constant="true"/>
        </listOfProducts>
        <listOfModifiers>
          <modifierSpeciesReference metaid="metaid_24" species="p"/>
        </listOfModifiers>
        <kineticLaw>
          <math xmlns="http://www.w3.org/1998/Math/MathML">
            <apply>
              <times/>
              <ci> k3 </ci>
              <ci> gamma </ci>
            </apply>
          </math>
        </kineticLaw>
      </reaction>
    </listOfReactions>
  </model>
</sbml>